{"zabbix_export": {"date": "2020-02-29T02:04:23Z", "templates": [{"templates": [], "description": "", "tags": [{"tag": "WL", "value": "Yes"}], "items": [{"allow_traps": "0", "snmpv3_contextname": "", "ssl_cert_file": "", "inventory_link": "0", "query_fields": [], "http_proxy": "", "trends": "365d", "post_type": "0", "snmpv3_authpassphrase": "", "snmp_oid": "", "snmpv3_securitylevel": "0", "port": "", "ssl_key_file": "", "logtimefmt": "", "jmx_endpoint": "", "master_item": [], "delay": "60s", "publickey": "", "request_method": "0", "params": "", "follow_redirects": "1", "units": "", "verify_host": "0", "type": "0", "snmpv3_authprotocol": "0", "valuemap": [], "ipmi_sensor": "", "username": "", "authtype": "0", "snmp_community": "", "description": "", "output_format": "0", "status_codes": "200", "allowed_hosts": "", "snmpv3_securityname": "", "preprocessing": [], "value_type": "3", "key": "db.version.date", "retrieve_mode": "0", "privatekey": "", "ssl_key_password": "", "password": "", "snmpv3_privpassphrase": "", "snmpv3_privprotocol": "0", "name": "Webfilter db version date", "applications": [{"name": "Zabbix agent custom parameter"}], "url": "", "posts": "", "headers": [], "status": "0", "timeout": "3s", "verify_peer": "0", "history": "90d"}, {"allow_traps": "0", "snmpv3_contextname": "", "ssl_cert_file": "", "inventory_link": "0", "query_fields": [], "http_proxy": "", "trends": "0", "post_type": "0", "snmpv3_authpassphrase": "", "snmp_oid": "", "snmpv3_securitylevel": "0", "port": "", "ssl_key_file": "", "logtimefmt": "", "jmx_endpoint": "", "master_item": [], "delay": "60s", "publickey": "", "request_method": "0", "params": "", "follow_redirects": "1", "units": "", "verify_host": "0", "type": "19", "snmpv3_authprotocol": "0", "valuemap": [], "ipmi_sensor": "", "username": "", "authtype": "0", "snmp_community": "", "description": "The complete output of of the monit system in json format (generated by the custom python process listening on port 2813.)", "output_format": "0", "status_codes": "200", "allowed_hosts": "", "snmpv3_securityname": "", "preprocessing": [], "value_type": "4", "key": "webfilter.monit", "retrieve_mode": "0", "privatekey": "", "ssl_key_password": "", "password": "", "snmpv3_privpassphrase": "", "snmpv3_privprotocol": "0", "name": "Webfilter monit complete output (json monit)", "applications": [{"name": "HTTP check"}], "url": "http://{HOST.HOST}:2813", "posts": "", "headers": [], "status": "0", "timeout": "5s", "verify_peer": "0", "history": "90d"}, {"allow_traps": "0", "snmpv3_contextname": "", "ssl_cert_file": "", "inventory_link": "0", "query_fields": [], "http_proxy": "", "trends": "0", "post_type": "0", "snmpv3_authpassphrase": "", "snmp_oid": "", "snmpv3_securitylevel": "0", "port": "", "ssl_key_file": "", "logtimefmt": "", "jmx_endpoint": "", "master_item": {"key": "webfilter.monit"}, "delay": "0", "publickey": "", "request_method": "0", "params": "", "follow_redirects": "1", "units": "", "verify_host": "0", "type": "18", "snmpv3_authprotocol": "0", "valuemap": [], "ipmi_sensor": "", "username": "", "authtype": "0", "snmp_community": "", "description": "", "output_format": "0", "status_codes": "200", "allowed_hosts": "", "snmpv3_securityname": "", "preprocessing": [{"error_handler_params": "", "type": "12", "error_handler": "0", "params": "$['status']"}, {"error_handler_params": "", "type": "5", "error_handler": "0", "params": "(.*)\n\\1:ok=0:degraded=1:fail=2"}, {"error_handler_params": "3", "type": "5", "error_handler": "2", "params": "(ok|degraded|fail)(?=.*:\\1=(\\d))\n\\2"}], "value_type": "4", "key": "webfilter.monit.overall.status", "retrieve_mode": "0", "privatekey": "", "ssl_key_password": "", "password": "", "snmpv3_privpassphrase": "", "snmpv3_privprotocol": "0", "name": "Webfillter overall status", "applications": [{"name": "HTTP check"}], "url": "", "posts": "", "headers": [], "status": "0", "timeout": "3s", "verify_peer": "0", "history": "90d"}], "httptests": [], "screens": [], "applications": [{"name": "HTTP check"}, {"name": "Zabbix agent custom parameter"}], "discovery_rules": [], "groups": [{"name": "Webfilter nodes"}], "template": "Template App Webfilter", "macros": [], "name": "Template App Webfilter"}], "version": "4.2", "groups": [{"name": "Webfilter nodes"}], "triggers": [{"status": "0", "recovery_mode": "0", "description": "", "tags": [], "url": "", "type": "0", "priority": "3", "correlation_tag": "", "dependencies": [], "correlation_mode": "0", "manual_close": "0", "expression": "{Template App Webfilter:db.version.date.fuzzytime(2d)}=0", "recovery_expression": "", "name": "Webfilter dB version is more than 2 days old"}, {"status": "0", "recovery_mode": "0", "description": "At least one of the monitored (monit) programs of processes is showing a failed state.  The system is degraded.", "tags": [], "url": "", "type": "0", "priority": "4", "correlation_tag": "", "dependencies": [], "correlation_mode": "0", "manual_close": "0", "expression": "{Template App Webfilter:webfilter.monit.overall.status.last()}=1", "recovery_expression": "", "name": "Webfilter status"}, {"status": "0", "recovery_mode": "0", "description": "All of the monitored (monit) programs of processes is showing a failed state.  The system is failed..", "tags": [], "url": "", "type": "0", "priority": "5", "correlation_tag": "", "dependencies": [], "correlation_mode": "0", "manual_close": "0", "expression": "{Template App Webfilter:webfilter.monit.overall.status.last()}=2", "recovery_expression": "", "name": "Webfilter status"}]}}