{"zabbix_export": {"date": "2020-02-29T02:04:34Z", "version": "4.2", "hosts": [{"status": "0", "groups": [{"name": "Discovered hosts"}, {"name": "grafana"}, {"name": "grafana - wl"}, {"name": "Linux nodes"}, {"name": "notifications - wl"}, {"name": "opsguest - wl"}, {"name": "Portal nodes"}], "ipmi_username": "", "httptests": [{"status": "0", "verify_host": "0", "name": "Policy engine API status", "application": {"name": "Cachet"}, "variables": [], "http_proxy": "", "attempts": "1", "agent": "Mozilla/5.0 (Windows NT 6.1; WOW64) AppleWebKit/537.36 (KHTML, like Gecko) Chrome/38.0.2125.104 Safari/537.36", "delay": "1m", "headers": [], "authentication": "1", "steps": [{"name": "Policy engine API status - 1", "url": "https://vsd01.prod-hvns-na01.internal:8443/nuage/api/v5_0/me", "follow_redirects": "1", "variables": [], "required": "", "posts": "", "headers": [], "query_fields": [], "timeout": "15s", "retrieve_mode": "0", "status_codes": "200"}, {"name": "Policy engine API status - 2", "url": "https://vsd02.prod-hvns-na01.internal:8443/nuage/api/v5_0/me", "follow_redirects": "1", "variables": [], "required": "", "posts": "", "headers": [], "query_fields": [], "timeout": "15s", "retrieve_mode": "0", "status_codes": "200"}, {"name": "Policy engine API status - 3", "url": "https://vsd03.prod-hvns-na01.internal:8443/nuage/api/v5_0/me", "follow_redirects": "1", "variables": [], "required": "", "posts": "", "headers": [], "query_fields": [], "timeout": "15s", "retrieve_mode": "0", "status_codes": "200"}], "http_user": "zabbix", "ssl_cert_file": "", "ssl_key_password": "", "verify_peer": "0", "http_password": "guZb$jrz$w5U", "ssl_key_file": ""}, {"status": "0", "verify_host": "0", "name": "Policy engine status", "application": {"name": "Cachet"}, "variables": [], "http_proxy": "", "attempts": "1", "agent": "Mozilla/5.0 (Windows NT 6.1; WOW64) AppleWebKit/537.36 (KHTML, like Gecko) Chrome/38.0.2125.104 Safari/537.36", "delay": "1m", "headers": [], "authentication": "1", "steps": [{"name": "Policy engine cluster status - 1", "url": "https://vsd01.prod-hvns-na01.internal:8443/nuage/health", "follow_redirects": "1", "variables": [], "required": "GOOD", "posts": "", "headers": [], "query_fields": [], "timeout": "15s", "retrieve_mode": "0", "status_codes": "200"}, {"name": "Policy engine cluster status - 2", "url": "https://vsd02.prod-hvns-na01.internal:8443/nuage/health", "follow_redirects": "1", "variables": [], "required": "GOOD", "posts": "", "headers": [], "query_fields": [], "timeout": "15s", "retrieve_mode": "0", "status_codes": "200"}, {"name": "Policy engine cluster status - 3", "url": "https://vsd03.prod-hvns-na01.internal:8443/nuage/health", "follow_redirects": "1", "variables": [], "required": "GOOD", "posts": "", "headers": [], "query_fields": [], "timeout": "15s", "retrieve_mode": "0", "status_codes": "200"}], "http_user": "zabbix", "ssl_cert_file": "", "ssl_key_password": "", "verify_peer": "0", "http_password": "guZb$jrz$w5U", "ssl_key_file": ""}], "ipmi_authtype": "-1", "discovery_rules": [], "tls_psk": "", "ipmi_privilege": "2", "macros": [], "inventory": {"inventory_mode": "-1"}, "templates": [{"name": "Template App Portal server"}, {"name": "Template OS Linux"}], "description": "", "tags": [{"tag": "WL", "value": "Yes"}], "interfaces": [{"default": "1", "ip": "", "useip": "0", "bulk": "1", "dns": "portal01.prod-hvns-na01.internal", "type": "1", "port": "10050", "interface_ref": "if1"}], "tls_accept": "1", "applications": [{"name": "Cachet"}], "host": "portal01.prod-hvns-na01.internal", "proxy": [], "ipmi_password": "", "tls_issuer": "", "tls_psk_identity": "", "name": "portal01.prod-hvns-na01.internal", "items": [], "tls_connect": "1", "tls_subject": ""}], "groups": [{"name": "Discovered hosts"}, {"name": "grafana"}, {"name": "grafana - wl"}, {"name": "Linux nodes"}, {"name": "notifications - wl"}, {"name": "opsguest - wl"}, {"name": "Portal nodes"}]}}